<?xml version="1.0" encoding="utf-8"?>
<DocumentElement><ESP><GRUP>INFO</GRUP><ID>0002AB8F</ID><EDID></EDID><CHAMP>NAM1</CHAMP><ORIGINAL>Do you get to the Cloud District very often? Oh, what am I saying - of course you don't.</ORIGINAL><TRADUIT>Passez-vous souvent dans le Quartier des Nuées ? Oh, mais qu'est-ce que je raconte ? Bien sûr que non.</TRADUIT><INDEX>1</INDEX><STATUS>99</STATUS><IDSTEXTE>NPC : Nazeem [00013BBF] (file)
Comment (NAM2) :  
EmotionType : Neutral</IDSTEXTE><COMMENTAIRE/><ICON>10</ICON></ESP><ESP><GRUP>INFO</GRUP><ID>0003627F</ID><EDID></EDID><CHAMP>NAM1</CHAMP><ORIGINAL>They don't like us talking to people when we work.</ORIGINAL><TRADUIT>Ils n'aiment pas que nous parlions à d'autres personnes lorsque nous travaillons.</TRADUIT><INDEX>1</INDEX><STATUS>99</STATUS><IDSTEXTE>NPC : Hathrasil [0001339C] (file)
EmotionType : Anger</IDSTEXTE><COMMENTAIRE/><ICON>10</ICON></ESP><ESP><GRUP>INFO</GRUP><ID>00036281</ID><EDID></EDID><CHAMP>NAM1</CHAMP><ORIGINAL>Busy with the smelter.</ORIGINAL><TRADUIT>Je suis occupé à la fonderie.</TRADUIT><INDEX>1</INDEX><STATUS>99</STATUS><IDSTEXTE>NPC : Hathrasil [0001339C] (file)
EmotionType : Anger</IDSTEXTE><COMMENTAIRE/><ICON>10</ICON></ESP><ESP><GRUP>INFO</GRUP><ID>00036280</ID><EDID></EDID><CHAMP>NAM1</CHAMP><ORIGINAL>Got metal to shape.</ORIGINAL><TRADUIT>J'ai du métal à forger.</TRADUIT><INDEX>1</INDEX><STATUS>99</STATUS><IDSTEXTE>NPC : Hathrasil [0001339C] (file)
EmotionType : Anger</IDSTEXTE><COMMENTAIRE/><ICON>10</ICON></ESP><ESP><GRUP>INFO</GRUP><ID>00036284</ID><EDID></EDID><CHAMP>NAM1</CHAMP><ORIGINAL>Can't talk. Mulush will beat me if I stop working.</ORIGINAL><TRADUIT>Je ne peux pas vous parler. Mulush me frappera si je m'arrête de travailler.</TRADUIT><INDEX>1</INDEX><STATUS>99</STATUS><IDSTEXTE>NPC : Omluag [000133AE] (file)
EmotionType : Anger</IDSTEXTE><COMMENTAIRE/><ICON>10</ICON></ESP><ESP><GRUP>INFO</GRUP><ID>00036285</ID><EDID></EDID><CHAMP>NAM1</CHAMP><ORIGINAL>Can't you see I'm working? Beat it.</ORIGINAL><TRADUIT>Vous ne voyez pas que je travaille ? Fichez le camp.</TRADUIT><INDEX>1</INDEX><STATUS>99</STATUS><IDSTEXTE>NPC : Omluag [000133AE] (file)
EmotionType : Anger</IDSTEXTE><COMMENTAIRE/><ICON>10</ICON></ESP></DocumentElement>
